countries_states_cities/__init__.py
countries_states_cities/admin.py
countries_states_cities/apps.py
countries_states_cities/filters.py
countries_states_cities/models.py
countries_states_cities/resource.py
countries_states_cities/serializers.py
countries_states_cities/settings.py
countries_states_cities/tests.py
countries_states_cities/translation.py
countries_states_cities/urls.py
countries_states_cities/utils.py
countries_states_cities/views.py
countries_states_cities/fixtures/csc_cities.csv
countries_states_cities/fixtures/csc_countries.csv
countries_states_cities/fixtures/csc_regions.csv
countries_states_cities/fixtures/csc_states.csv
countries_states_cities/fixtures/csc_subregions.csv
countries_states_cities/management/__init__.py
countries_states_cities/management/__pycache__/__init__.cpython-310.pyc
countries_states_cities/management/commands/__init__.py
countries_states_cities/management/commands/csc_dumpdata_csv.py
countries_states_cities/management/commands/csc_loaddata_csv.py
countries_states_cities/management/commands/__pycache__/__init__.cpython-310.pyc
countries_states_cities/management/commands/__pycache__/csc_loaddata_csv.cpython-310.pyc
django_countries_states_cities-1.0.23.dist-info/LICENSE
django_countries_states_cities-1.0.23.dist-info/METADATA
django_countries_states_cities-1.0.23.dist-info/WHEEL
django_countries_states_cities-1.0.23.dist-info/top_level.txt
django_countries_states_cities-1.0.23.dist-info/RECORD
