Metadata-Version: 2.2
Name: django-countries-states-cities
Version: 1.0.23
Summary: Countries States Cities models for Django.
Home-page: https://github.com/runners-2022/django-countries-states-cities
Author: Sunwook Kim
Author-email: Sunwook Kim <sun@runners.im>
License: MIT
Project-URL: Homepage, https://github.com/runners-2022/django-countries-states-cities
Requires-Python: >=3.8
License-File: LICENSE
Requires-Dist: Django<4.0,>=3.2.16
Requires-Dist: django-filter<23.0,>=22.1
Requires-Dist: django-import-export<3.0,>=2.9.0
Requires-Dist: django-modeltranslation<0.19,>=0.18.11
Requires-Dist: django-url-filter<0.4,>=0.3.15
Requires-Dist: djangorestframework<3.15,>=3.14.0
Requires-Dist: drf-yasg<1.22,>=1.21.4
Requires-Dist: requests<3.0,>=2.32.3
Requires-Dist: urllib3<3,>=1.26.5
